{
  "version": "7",
  "dialect": "mysql",
  "entries": [
    {
      "idx": 0,
      "version": "5",
      "when": 1768655942195,
      "tag": "0000_open_brother_voodoo",
      "breakpoints": true
    },
    {
      "idx": 1,
      "version": "5",
      "when": 1768655999263,
      "tag": "0001_legal_living_lightning",
      "breakpoints": true
    },
    {
      "idx": 2,
      "version": "5",
      "when": 1768658754067,
      "tag": "0002_fearless_leader",
      "breakpoints": true
    },
    {
      "idx": 3,
      "version": "5",
      "when": 1768745494052,
      "tag": "0003_magenta_colonel_america",
      "breakpoints": true
    },
    {
      "idx": 4,
      "version": "5",
      "when": 1768750197649,
      "tag": "0004_lucky_gambit",
      "breakpoints": true
    }
  ]
}